examples/virtual-led-counter/src/virtual_led_counter.sv
module virtual_led_counter (
  input  logic       clk,
  input  logic       reset,
  input  logic       enable,
  input  logic       button,
  output logic [3:0] leds
);
  always_ff @(posedge clk) begin
    if (reset)
      leds <= 4'b0000;
    else if (enable || button)
      leds <= leds + 4'b0001;
  end
endmodule

examples/virtual-led-counter/sim/virtual-fpga.vcd
$version Generated by VerilatedVcd $end
$timescale 1ps $end
 $scope module TOP $end
  $var wire 1 " clk $end
  $var wire 1 # reset $end
  $var wire 1 $ enable $end
  $var wire 1 % button $end
  $var wire 4 & leds [3:0] $end
  $scope module virtual_led_counter $end
   $var wire 1 " clk $end
   $var wire 1 # reset $end
   $var wire 1 $ enable $end
   $var wire 1 % button $end
   $var wire 4 & leds [3:0] $end
  $upscope $end
 $upscope $end
$enddefinitions $end


#0
0"
0#
0$
0%
b0000 &
#1
1"
1$
b0001 &
#2
0"
#3
1"
b0010 &
#4
0"
#5
1"
b0011 &
#6
0"
#7
1"
b0100 &
#8
0"
#9
1"
b0101 &
#10
0"
#11
1"
b0110 &
#12
0"
#13
1"
b0111 &
#14
0"
#15
1"
b1000 &
#16
0"
#17
1"
b1001 &
#18
0"
#19
1"
b1010 &
#20
0"
#21
1"
b1011 &
#22
0"
#23
1"
b1100 &
#24
0"
#25
1"
b1101 &
#26
0"
#27
1"
b1110 &
#28
0"
#29
1"
b1111 &
#30
0"
#31
1"
b0000 &
#32
0"
#33
1"
b0001 &
#34
0"
#35
1"
b0010 &
#36
0"
#37
1"
b0011 &
#38
0"
#39
1"
b0100 &
#40
0"
#41
1"
b0101 &
#42
0"
#43
1"
b0110 &
#44
0"
#45
1"
b0111 &
#46
0"
#47
1"
b1000 &
#48
0"
#49
1"
b1001 &
#50
0"
#51
1"
b1010 &
#52
0"
#53
1"
b1011 &
#54
0"
#55
1"
b1100 &
#56
0"
#57
1"
b1101 &
#58
0"
#59
1"
b1110 &
#60
0"
#61
1"
b1111 &
#62
0"
#63
1"
b0000 &
#64
0"
#65
1"
b0001 &
#66
0"
#67
1"
b0010 &
#68
0"
#69
1"
b0011 &
#70
0"
#71
1"
b0100 &
#72
0"
#73
1"
b0101 &
#74
0"
#75
1"
b0110 &
#76
0"
#77
1"
b0111 &
#78
0"
#79
1"
b1000 &
#80
0"
#81
1"
b1001 &
#82
0"
#83
1"
b1010 &
#84
0"
#85
1"
b1011 &
#86
0"
#87
1"
b1100 &
#88
0"
#89
1"
b1101 &
#90
0"
#91
1"
b1110 &
#92
0"
#93
1"
b1111 &
#94
0"
#95
1"
b0000 &
#96
0"
#97
1"
b0001 &
#98
0"
#99
1"
b0010 &
#100
0"
#101
1"
b0011 &
#102
0"
#103
1"
b0100 &
#104
0"
#105
1"
b0101 &
#106
0"
#107
1"
b0110 &
#108
0"
#109
1"
b0111 &
#110
0"
#111
1"
b1000 &
#112
0"
#113
1"
b1001 &
#114
0"
#115
1"
b1010 &
#116
0"
#117
1"
b1011 &
#118
0"
#119
1"
b1100 &
#120
0"
#121
1"
b1101 &
#122
0"
#123
1"
b1110 &
#124
0"
#125
1"
b1111 &
#126
0"
#127
1"
b0000 &
#128
0"
#129
1"
b0001 &
#130
0"
#131
1"
b0010 &
#132
0"
#133
1"
b0011 &
#134
0"
#135
1"
b0100 &
#136
0"
#137
1"
b0101 &
#138
0"
#139
1"
b0110 &
#140
0"
#141
1"
b0111 &
#142
0"
#143
1"
b1000 &
#144
0"
#145
1"
b1001 &
#146
0"
#147
1"
b1010 &
#148
0"
#149
1"
b1011 &
#150
0"
#151
1"
b1100 &
#152
0"
#153
1"
b1101 &
#154
0"
#155
1"
b1110 &
#156
0"
#157
1"
b1111 &
#158
0"
#159
1"
b0000 &
#160
0"
#161
1"
b0001 &
#162
0"
#163
1"
b0010 &
#164
0"
#165
1"
b0011 &
#166
0"
#167
1"
b0100 &
#168
0"
#169
1"
b0101 &
#170
0"
#171
1"
b0110 &
#172
0"
#173
1"
b0111 &
#174
0"
#175
1"
b1000 &
#176
0"
#177
1"
b1001 &
#178
0"
#179
1"
b1010 &
#180
0"
#181
1"
b1011 &
#182
0"
#183
1"
b1100 &
#184
0"
#185
1"
b1101 &
#186
0"
#187
1"
b1110 &
#188
0"
#189
1"
b1111 &
#190
0"
#191
1"
b0000 &
#192
0"
#193
1"
b0001 &
#194
0"
#195
1"
b0010 &
#196
0"
#197
1"
b0011 &
#198
0"
#199
1"
b0100 &
#200
0"
#201
1"
b0101 &
#202
0"
#203
1"
b0110 &
#204
0"
#205
1"
b0111 &
#206
0"
#207
1"
b1000 &
#208
0"
#209
1"
b1001 &
#210
0"
#211
1"
b1010 &
#212
0"
#213
1"
b1011 &
#214
0"
#215
1"
b1100 &
#216
0"
#217
1"
b1101 &
#218
0"
#219
1"
b1110 &
#220
0"
#221
1"
b1111 &
#222
0"
#223
1"
b0000 &
#224
0"
#225
1"
b0001 &
#226
0"
#227
1"
b0010 &
#228
0"
#229
1"
b0011 &
#230
0"
#231
1"
b0100 &
#232
0"
#233
1"
b0101 &
#234
0"
#235
1"
b0110 &
#236
0"
#237
1"
b0111 &
#238
0"
#239
1"
b1000 &
#240
0"
#241
1"
b1001 &
#242
0"
#243
1"
b1010 &
#244
0"
#245
1"
b1011 &
#246
0"
#247
1"
b1100 &
#248
0"
#249
1"
b1101 &
#250
0"
#251
1"
b1110 &
#252
0"
#253
1"
b1111 &
#254
0"
#255
1"
b0000 &
#256
0"
#257
1"
b0001 &
#258
0"
#259
1"
b0010 &
#260
0"
#261
1"
b0011 &
#262
0"
#263
1"
b0100 &
#264
0"
#265
1"
b0101 &
#266
0"
#267
1"
b0110 &
#268
0"
#269
1"
b0111 &
#270
0"
#271
1"
b1000 &
#272
0"
#273
1"
b1001 &
#274
0"
#275
1"
b1010 &
#276
0"
#277
1"
b1011 &
#278
0"
#279
1"
b1100 &
#280
0"
#281
1"
b1101 &
#282
0"
#283
1"
b1110 &
#284
0"
#285
1"
b1111 &
#286
0"
#287
1"
b0000 &
#288
0"
#289
1"
b0001 &
#290
0"
#291
1"
b0010 &
#292
0"
#293
1"
b0011 &
#294
0"
#295
1"
b0100 &
#296
0"
#297
1"
b0101 &
#298
0"
#299
1"
b0110 &
#300
0"
#301
1"
b0111 &
#302
0"
#303
1"
b1000 &
#304
0"
#305
1"
b1001 &
#306
0"
#307
1"
b1010 &
#308
0"
#309
1"
b1011 &
#310
0"
#311
1"
b1100 &
#312
0"
#313
1"
b1101 &
#314
0"
#315
1"
b1110 &
#316
0"
#317
1"
b1111 &
#318
0"
#319
1"
b0000 &
#320
0"
#321
1"
b0001 &
#322
0"
#323
1"
b0010 &
#324
0"
#325
1"
b0011 &
#326
0"
#327
1"
b0100 &
#328
0"
#329
1"
b0101 &
#330
0"
#331
1"
b0110 &
#332
0"
#333
1"
b0111 &
#334
0"
#335
1"
b1000 &
#336
0"
#337
1"
b1001 &
#338
0"
#339
1"
b1010 &
#340
0"
#341
1"
b1011 &
#342
0"
#343
1"
b1100 &
#344
0"
#345
1"
b1101 &
#346
0"
#347
1"
b1110 &
#348
0"
#349
1"
b1111 &
#350
0"
#351
1"
b0000 &
#352
0"
#353
1"
b0001 &
#354
0"
#355
1"
b0010 &
#356
0"
#357
1"
b0011 &
#358
0"
#359
1"
b0100 &
#360
0"
#361
1"
b0101 &
#362
0"
#363
1"
b0110 &
#364
0"
#365
1"
b0111 &
#366
0"
#367
1"
b1000 &
#368
0"
#369
1"
b1001 &
#370
0"
#371
1"
b1010 &
#372
0"
#373
1"
b1011 &
#374
0"
#375
1"
b1100 &
#376
0"
#377
1"
b1101 &
#378
0"
#379
1"
b1110 &
#380
0"
#381
1"
b1111 &
#382
0"
#383
1"
b0000 &
#384
0"
#385
1"
b0001 &
#386
0"
#387
1"
b0010 &
#388
0"
#389
1"
b0011 &
#390
0"
#391
1"
b0100 &
#392
0"
#393
1"
b0101 &
#394
0"
#395
1"
b0110 &
#396
0"
#397
1"
b0111 &
#398
0"
#399
1"
b1000 &
#400
0"
#401
1"
b1001 &
#402
0"
#403
1"
b1010 &
#404
0"
#405
1"
b1011 &
#406
0"
#407
1"
b1100 &
#408
0"
#409
1"
b1101 &
#410
0"
#411
1"
b1110 &
#412
0"
#413
1"
b1111 &
#414
0"
#415
1"
b0000 &
#416
0"
#417
1"
b0001 &
#418
0"
#419
1"
b0010 &
#420
0"
#421
1"
b0011 &
#422
0"
#423
1"
b0100 &
#424
0"
#425
1"
b0101 &
#426
0"
#427
1"
b0110 &
#428
0"
#429
1"
b0111 &
#430
0"
#431
1"
b1000 &
#432
0"
#433
1"
b1001 &
#434
0"
#435
1"
b1010 &
#436
0"
#437
1"
b1011 &
#438
0"
#439
1"
b1100 &
#440
0"
#441
1"
b1101 &
#442
0"
#443
1"
b1110 &
#444
0"
#445
1"
b1111 &
#446
0"
#447
1"
b0000 &
#448
0"
#449
1"
b0001 &
#450
0"
#451
1"
b0010 &
#452
0"
#453
1"
b0011 &
#454
0"
#455
1"
b0100 &
#456
0"
#457
1"
b0101 &
#458
0"
#459
1"
b0110 &
#460
0"
#461
1"
b0111 &
#462
0"
#463
1"
b1000 &
#464
0"
#465
1"
b1001 &
#466
0"
#467
1"
b1010 &
#468
0"
#469
1"
b1011 &
#470
0"
#471
1"
b1100 &
#472
0"
#473
1"
b1101 &
#474
0"
#475
1"
b1110 &
#476
0"
#477
1"
b1111 &
#478
0"
#479
1"
b0000 &
#480
0"
#481
1"
b0001 &
#482
0"
#483
1"
b0010 &
#484
0"
#485
1"
b0011 &
#486
0"
#487
1"
b0100 &
#488
0"
#489
1"
b0101 &
#490
0"
#491
1"
b0110 &
#492
0"
#493
1"
b0111 &
#494
0"
#495
1"
b1000 &
#496
0"
#497
1"
b1001 &
#498
0"
#499
1"
b1010 &
#500
0"
#501
1"
b1011 &
#502
0"
#503
1"
b1100 &
#504
0"
#505
1"
b1101 &
#506
0"
#507
1"
b1110 &
#508
0"
#509
1"
b1111 &
#510
0"
#511
1"
b0000 &
#512
0"
#513
1"
b0001 &
#514
0"
#515
1"
b0010 &
#516
0"
#517
1"
b0011 &
#518
0"
#519
1"
b0100 &
#520
0"
#521
1"
b0101 &
#522
0"
#523
1"
b0110 &
#524
0"
#525
1"
b0111 &
#526
0"
#527
1"
b1000 &
#528
0"
#529
1"
b1001 &
#530
0"
#531
1"
b1010 &
#532
0"
#533
1"
b1011 &
#534
0"
#535
1"
b1100 &
#536
0"
#537
1"
b1101 &
#538
0"
#539
1"
b1110 &
#540
0"
#541
1"
b1111 &
#542
0"
#543
1"
b0000 &
#544
0"
#545
1"
b0001 &
#546
0"
#547
1"
b0010 &
#548
0"
#549
1"
b0011 &
#550
0"
#551
1"
b0100 &
#552
0"
#553
1"
b0101 &
#554
0"
#555
1"
b0110 &
#556
0"
#557
1"
b0111 &
#558
0"
#559
1"
b1000 &
#560
0"
#561
1"
b1001 &
#562
0"
#563
1"
b1010 &
#564
0"
#565
1"
b1011 &
#566
0"
#567
1"
b1100 &
#568
0"
#569
1"
b1101 &
#570
0"
#571
1"
b1110 &
#572
0"
#573
1"
b1111 &
#574
0"
#575
1"
b0000 &
#576
0"
#577
1"
b0001 &
#578
0"
#579
1"
b0010 &
#580
0"
#581
1"
b0011 &
#582
0"
#583
1"
b0100 &
#584
0"
#585
1"
b0101 &
#586
0"
#587
1"
b0110 &
#588
0"
#589
1"
b0111 &
#590
0"
#591
1"
b1000 &
#592
0"
#593
1"
b1001 &
#594
0"
#595
1"
b1010 &
#596
0"
#597
1"
b1011 &
#598
0"
#599
1"
b1100 &
#600
0"
#601
1"
b1101 &
#602
0"
#603
1"
b1110 &
#604
0"
#605
1"
b1111 &
#606
0"
#607
1"
b0000 &
#608
0"
#609
1"
b0001 &
#610
0"
#611
1"
b0010 &
#612
0"
#613
1"
b0011 &
#614
0"
#615
1"
b0100 &
#616
0"
#617
1"
b0101 &
#618
0"
#619
1"
b0110 &
#620
0"
#621
1"
b0111 &
#622
0"
#623
1"
b1000 &
#624
0"
#625
1"
b1001 &
#626
0"
#627
1"
b1010 &
#628
0"
#629
1"
b1011 &
#630
0"
#631
1"
b1100 &
#632
0"
#633
1"
b1101 &
#634
0"
#635
1"
b1110 &
#636
0"
#637
1"
b1111 &
#638
0"
#639
1"
b0000 &
#640
0"
#641
1"
b0001 &
#642
0"
#643
1"
b0010 &
#644
0"
#645
1"
b0011 &
#646
0"
#647
1"
b0100 &
#648
0"
#649
1"
b0101 &
#650
0"
#651
1"
b0110 &
#652
0"
#653
1"
b0111 &
#654
0"
#655
1"
b1000 &
#656
0"
#657
1"
b1001 &
#658
0"
#659
1"
b1010 &
#660
0"
#661
1"
b1011 &
#662
0"
#663
1"
b1100 &
#664
0"
#665
1"
b1101 &
#666
0"
#667
1"
b1110 &
#668
0"
#669
1"
b1111 &
#670
0"
#671
1"
b0000 &
#672
0"
#673
1"
b0001 &
#674
0"
#675
1"
b0010 &
#676
0"
#677
1"
b0011 &
#678
0"
#679
1"
b0100 &
#680
0"
#681
1"
b0101 &
#682
0"
#683
1"
b0110 &
#684
0"
#685
1"
b0111 &
#686
0"
#687
1"
b1000 &
#688
0"
#689
1"
b1001 &
#690
0"
#691
1"
b1010 &
#692
0"
#693
1"
b1011 &
#694
0"
#695
1"
b1100 &
#696
0"
#697
1"
b1101 &
#698
0"
#699
1"
b1110 &
#700
0"
#701
1"
b1111 &
#702
0"
#703
1"
b0000 &
#704
0"
#705
1"
b0001 &
#706
0"
#707
1"
b0010 &
#708
0"
#709
1"
b0011 &
#710
0"
#711
1"
b0100 &
#712
0"
#713
1"
b0101 &
#714
0"
#715
1"
b0110 &
#716
0"
#717
1"
b0111 &
#718
0"
#719
1"
b1000 &
#720
0"
#721
1"
b1001 &
#722
0"
#723
1"
b1010 &
#724
0"
#725
1"
b1011 &
#726
0"
#727
1"
b1100 &
#728
0"
#729
1"
b1101 &
#730
0"
#731
1"
b1110 &
#732
0"
#733
1"
b1111 &
#734
0"
#735
1"
b0000 &
#736
0"
#737
1"
b0001 &
#738
0"
#739
1"
b0010 &
#740
0"
#741
1"
b0011 &
#742
0"
#743
1"
b0100 &
#744
0"
#745
1"
b0101 &
#746
0"
#747
1"
b0110 &
#748
0"
#749
1"
b0111 &
#750
0"
#751
1"
b1000 &
#752
0"
#753
1"
b1001 &
#754
0"
#755
1"
b1010 &
#756
0"
#757
1"
b1011 &
#758
0"
#759
1"
b1100 &
#760
0"
#761
1"
b1101 &
#762
0"
#763
1"
b1110 &
#764
0"
#765
1"
b1111 &
#766
0"
#767
1"
b0000 &
#768
0"
#769
1"
b0001 &
#770
0"
#771
1"
b0010 &
#772
0"
#773
1"
b0011 &
#774
0"
#775
1"
b0100 &
#776
0"
#777
1"
b0101 &
#778
0"
#779
1"
b0110 &
#780
0"
#781
1"
b0111 &
#782
0"
#783
1"
b1000 &
#784
0"
#785
1"
b1001 &
#786
0"
#787
1"
b1010 &
#788
0"
#789
1"
b1011 &
#790
0"
#791
1"
b1100 &
#792
0"
#793
1"
b1101 &
#794
0"
#795
1"
b1110 &
#796
0"
#797
1"
b1111 &
#798
0"
#799
1"
b0000 &
#800
0"
#801
1"
b0001 &
#802
0"
#803
1"
b0010 &
#804
0"
#805
1"
b0011 &
#806
0"
#807
1"
b0100 &
#808
0"
#809
1"
b0101 &
#810
0"
#811
1"
b0110 &
#812
0"
#813
1"
b0111 &
#814
0"
#815
1"
b1000 &
#816
0"
#817
1"
b1001 &
#818
0"
#819
1"
b1010 &
#820
0"
#821
1"
b1011 &
#822
0"
#823
1"
b1100 &
#824
0"
#825
1"
b1101 &
#826
0"
#827
1"
b1110 &
#828
0"
#829
1"
b1111 &
#830
0"
#831
1"
b0000 &
#832
0"
#833
1"
b0001 &
#834
0"
#835
1"
b0010 &
#836
0"
#837
1"
b0011 &
#838
0"
#839
1"
b0100 &
#840
0"
#841
1"
b0101 &
#842
0"
#843
1"
b0110 &
#844
0"
#845
1"
b0111 &
#846
0"
#847
1"
b1000 &
#848
0"
#849
1"
b1001 &
#850
0"
#851
1"
b1010 &
#852
0"
#853
1"
b1011 &
#854
0"
#855
1"
b1100 &
#856
0"
#857
1"
b1101 &
#858
0"
#859
1"
b1110 &
#860
0"
#861
1"
b1111 &
#862
0"
#863
1"
b0000 &
#864
0"
#865
1"
b0001 &
#866
0"
#867
1"
b0010 &
#868
0"
#869
1"
b0011 &
#870
0"
#871
1"
b0100 &
#872
0"
#873
1"
b0101 &
#874
0"
#875
1"
b0110 &
#876
0"
#877
1"
b0111 &
#878
0"
#879
1"
b1000 &
#880
0"
#881
1"
b1001 &
#882
0"
#883
1"
b1010 &
#884
0"
#885
1"
b1011 &
#886
0"
#887
1"
b1100 &
#888
0"
#889
1"
b1101 &
#890
0"
#891
1"
b1110 &
#892
0"
#893
1"
b1111 &
#894
0"
#895
1"
b0000 &
#896
0"
#897
1"
b0001 &
#898
0"
#899
1"
b0010 &
#900
0"
#901
1"
b0011 &
#902
0"
#903
1"
b0100 &
#904
0"
#905
1"
b0101 &
#906
0"
#907
1"
b0110 &
#908
0"
#909
1"
b0111 &
#910
0"
#911
1"
b1000 &
#912
0"
#913
1"
b1001 &
#914
0"
#915
1"
b1010 &
#916
0"
#917
1"
b1011 &
#918
0"
#919
1"
b1100 &
#920
0"
#921
1"
b1101 &
#922
0"
#923
1"
b1110 &
#924
0"
#925
1"
b1111 &
#926
0"
#927
1"
b0000 &
#928
0"
#929
1"
b0001 &
#930
0"
#931
1"
b0010 &
#932
0"
#933
1"
b0011 &
#934
0"
#935
1"
b0100 &
#936
0"
#937
1"
b0101 &
#938
0"
#939
1"
b0110 &
#940
0"
#941
1"
b0111 &
#942
0"
#943
1"
b1000 &
#944
0"
#945
1"
b1001 &
#946
0"
#947
1"
b1010 &
#948
0"
#949
1"
b1011 &
#950
0"
#951
1"
b1100 &
#952
0"
#953
1"
b1101 &
#954
0"
#955
1"
b1110 &
#956
0"
#957
1"
b1111 &
#958
0"
#959
1"
b0000 &
#960
0"
#961
1"
b0001 &
#962
0"
#963
1"
b0010 &
#964
0"
#965
1"
b0011 &
#966
0"
#967
1"
b0100 &
#968
0"
#969
1"
b0101 &
#970
0"
#971
1"
b0110 &
#972
0"
#973
1"
b0111 &
#974
0"
#975
1"
b1000 &
#976
0"
#977
1"
b1001 &
#978
0"
#979
1"
b1010 &
#980
0"
#981
1"
b1011 &
#982
0"
#983
1"
b1100 &
#984
0"
#985
1"
b1101 &
#986
0"
#987
1"
b1110 &
#988
0"
#989
1"
b1111 &
#990
0"
#991
1"
b0000 &
#992
0"
#993
1"
b0001 &
#994
0"
#995
1"
b0010 &
#996
0"
#997
1"
b0011 &
#998
0"
#999
1"
b0100 &
#1000
0"
#1001
1"
b0101 &
#1002
0"
#1003
1"
b0110 &
#1004
0"
#1005
1"
b0111 &
#1006
0"
#1007
1"
b1000 &
#1008
0"
#1009
1"
b1001 &
#1010
0"
#1011
1"
b1010 &
#1012
0"
#1013
1"
b1011 &
#1014
0"
#1015
1"
b1100 &
#1016
0"
#1017
1"
b1101 &
#1018
0"
#1019
1"
b1110 &
#1020
0"
#1021
1"
b1111 &
#1022
0"
#1023
1"
b0000 &
#1024
0"
#1025
1"
b0001 &
#1026
0"
#1027
1"
b0010 &
#1028
0"
#1029
1"
b0011 &
#1030
0"
#1031
1"
b0100 &
#1032
0"
#1033
1"
b0101 &
#1034
0"
#1035
1"
b0110 &
#1036
0"
#1037
1"
b0111 &
#1038
0"
#1039
1"
b1000 &
#1040
0"
#1041
1"
b1001 &
#1042
0"
#1043
1"
b1010 &
#1044
0"
#1045
1"
b1011 &
#1046
0"
#1047
1"
b1100 &
#1048
0"
#1049
1"
b1101 &
#1050
0"
#1051
1"
b1110 &
#1052
0"
#1053
1"
b1111 &
#1054
0"
#1055
1"
b0000 &
#1056
0"
#1057
1"
b0001 &
#1058
0"
#1059
1"
b0010 &
#1060
0"
#1061
1"
b0011 &
#1062
0"
#1063
1"
b0100 &
#1064
0"
#1065
1"
b0101 &
#1066
0"
#1067
1"
b0110 &
#1068
0"
#1069
1"
b0111 &
#1070
0"
#1071
1"
b1000 &
#1072
0"
#1073
1"
b1001 &
#1074
0"
#1075
1"
b1010 &
#1076
0"
#1077
1"
b1011 &
#1078
0"
#1079
1"
b1100 &
#1080
0"
#1081
1"
b1101 &
#1082
0"
#1083
1"
b1110 &
#1084
0"
#1085
1"
b1111 &
#1086
0"
#1087
1"
b0000 &
#1088
0"
#1089
1"
b0001 &
#1090
0"
#1091
1"
b0010 &
#1092
0"
#1093
1"
b0011 &
#1094
0"
#1095
1"
b0100 &
#1096
0"
#1097
1"
b0101 &
#1098
0"
#1099
1"
b0110 &
#1100
0"
#1101
1"
b0111 &
#1102
0"
#1103
1"
b1000 &
#1104
0"
#1105
1"
b1001 &
#1106
0"
#1107
1"
b1010 &
#1108
0"
#1109
1"
b1011 &
#1110
0"
#1111
1"
b1100 &
#1112
0"
#1113
1"
b1101 &
#1114
0"
#1115
1"
b1110 &
#1116
0"
#1117
1"
b1111 &
#1118
0"
#1119
1"
b0000 &
#1120
0"
#1121
1"
b0001 &
#1122
0"
#1123
1"
b0010 &
#1124
0"
#1125
1"
b0011 &
#1126
0"
#1127
1"
b0100 &
#1128
0"
#1129
1"
b0101 &
#1130
0"
#1131
1"
b0110 &
#1132
0"
#1133
1"
b0111 &
#1134
0"
#1135
1"
b1000 &
#1136
0"
#1137
1"
b1001 &
#1138
0"
#1139
1"
b1010 &
#1140
0"
#1141
1"
b1011 &
#1142
0"
#1143
1"
b1100 &
#1144
0"
#1145
1"
b1101 &
#1146
0"
#1147
1"
b1110 &
#1148
0"
#1149
1"
b1111 &
#1150
0"
#1151
1"
b0000 &
#1152
0"
#1153
1"
b0001 &
#1154
0"
#1155
1"
b0010 &
#1156
0"
#1157
1"
b0011 &
#1158
0"
#1159
1"
b0100 &
#1160
0"
#1161
1"
b0101 &
#1162
0"
#1163
1"
b0110 &
#1164
0"
#1165
1"
b0111 &
#1166
0"
#1167
1"
b1000 &
#1168
0"
#1169
1"
b1001 &
#1170
0"
#1171
1"
b1010 &
#1172
0"
#1173
1"
b1011 &
#1174
0"
#1175
1"
b1100 &
#1176
0"
#1177
1"
b1101 &
#1178
0"
#1179
1"
b1110 &
#1180
0"
#1181
1"
b1111 &
#1182
0"
#1183
1"
b0000 &
#1184
0"
#1185
1"
b0001 &
#1186
0"
#1187
1"
b0010 &
#1188
0"
#1189
1"
b0011 &
#1190
0"
#1191
1"
b0100 &
#1192
0"
#1193
1"
b0101 &
#1194
0"
#1195
1"
b0110 &
#1196
0"
#1197
1"
b0111 &
#1198
0"
#1199
1"
b1000 &
#1200
0"
#1201
1"
b1001 &
#1202
0"
#1203
1"
b1010 &
#1204
0"
#1205
1"
b1011 &
#1206
0"
#1207
1"
b1100 &
#1208
0"
#1209
1"
b1101 &
#1210
0"
#1211
1"
b1110 &
#1212
0"
#1213
1"
b1111 &
#1214
0"
#1215
1"
b0000 &
#1216
0"
#1217
1"
b0001 &
#1218
0"
#1219
1"
b0010 &
#1220
0"
#1221
1"
b0011 &
#1222
0"
#1223
1"
b0100 &
#1224
0"
#1225
1"
b0101 &
#1226
0"
#1227
1"
b0110 &
#1228
0"
#1229
1"
b0111 &
#1230
0"
#1231
1"
b1000 &
#1232
0"
#1233
1"
b1001 &
#1234
0"
#1235
1"
b1010 &
#1236
0"
#1237
1"
b1011 &
#1238
0"
#1239
1"
b1100 &
#1240
0"
#1241
1"
b1101 &
#1242
0"
#1243
1"
b1110 &
#1244
0"
#1245
1"
b1111 &
#1246
0"
#1247
1"
b0000 &
#1248
0"
#1249
1"
b0001 &
#1250
0"
#1251
1"
b0010 &
#1252
0"
#1253
1"
b0011 &
#1254
0"
#1255
1"
b0100 &
#1256
0"
#1257
1"
b0101 &
#1258
0"
#1259
1"
b0110 &
#1260
0"
#1261
1"
b0111 &
#1262
0"
#1263
1"
b1000 &
#1264
0"
#1265
1"
b1001 &
#1266
0"
#1267
1"
b1010 &
#1268
0"
#1269
1"
b1011 &
#1270
0"
#1271
1"
b1100 &
#1272
0"
#1273
1"
b1101 &
#1274
0"
#1275
1"
b1110 &
#1276
0"
#1277
1"
b1111 &
#1278
0"
#1279
1"
b0000 &
#1280
0"
#1281
1"
b0001 &
#1282
0"
#1283
1"
b0010 &
#1284
0"
#1285
1"
b0011 &
#1286
0"
#1287
1"
b0100 &
#1288
0"
#1289
1"
b0101 &
#1290
0"
#1291
1"
b0110 &
#1292
0"
#1293
1"
b0111 &
#1294
0"
#1295
1"
b1000 &
#1296
0"
#1297
1"
b1001 &
#1298
0"
#1299
1"
b1010 &
#1300
0"
#1301
1"
b1011 &
#1302
0"
#1303
1"
b1100 &
#1304
0"
#1305
1"
b1101 &
#1306
0"
#1307
1"
b1110 &
#1308
0"
#1309
1"
b1111 &
#1310
0"
#1311
1"
b0000 &
#1312
0"
#1313
1"
b0001 &
#1314
0"
#1315
1"
b0010 &
#1316
0"
#1317
1"
b0011 &
#1318
0"
#1319
1"
b0100 &
#1320
0"
#1321
1"
b0101 &
#1322
0"
#1323
1"
b0110 &
#1324
0"
#1325
1"
b0111 &
#1326
0"
#1327
1"
b1000 &
#1328
0"
#1329
1"
b1001 &
#1330
0"
#1331
1"
b1010 &
#1332
0"
#1333
1"
b1011 &
#1334
0"
#1335
1"
b1100 &
#1336
0"
#1337
1"
b1101 &
#1338
0"
#1339
1"
b1110 &
#1340
0"
#1341
1"
b1111 &
#1342
0"
#1343
1"
b0000 &
#1344
0"
#1345
1"
b0001 &
#1346
0"
#1347
1"
b0010 &
#1348
0"
#1349
1"
b0011 &
#1350
0"
#1351
1"
b0100 &
#1352
0"
#1353
1"
b0101 &
#1354
0"
#1355
1"
b0110 &
#1356
0"
#1357
1"
b0111 &
#1358
0"
#1359
1"
b1000 &
#1360
0"
#1361
1"
b1001 &
#1362
0"
#1363
1"
b1010 &
#1364
0"
#1365
1"
b1011 &
#1366
0"
#1367
1"
b1100 &
#1368
0"
#1369
1"
b1101 &
#1370
0"
#1371
1"
b1110 &
#1372
0"
#1373
1"
b1111 &
#1374
0"
#1375
1"
b0000 &
#1376
0"
#1377
1"
b0001 &
#1378
0"
#1379
1"
b0010 &
#1380
0"
#1381
1"
b0011 &
#1382
0"
#1383
1"
b0100 &
#1384
0"
#1385
1"
b0101 &
#1386
0"
#1387
1"
b0110 &
#1388
0"
#1389
1"
b0111 &
#1390
0"
#1391
1"
b1000 &
#1392
0"
#1393
1"
b1001 &
#1394
0"
#1395
1"
b1010 &
#1396
0"
#1397
1"
b1011 &
#1398
0"
#1399
1"
b1100 &
#1400
0"
#1401
1"
b1101 &
#1402
0"
#1403
1"
b1110 &
#1404
0"
#1405
1"
b1111 &
#1406
0"
#1407
1"
b0000 &
#1408
0"
#1409
1"
b0001 &
#1410
0"
#1411
1"
b0010 &
#1412
0"
#1413
1"
b0011 &
#1414
0"
#1415
1"
b0100 &
#1416
0"
#1417
1"
b0101 &
#1418
0"
#1419
1"
b0110 &
#1420
0"
#1421
1"
b0111 &
#1422
0"
#1423
1"
b1000 &
#1424
0"
#1425
1"
b1001 &
#1426
0"
#1427
1"
b1010 &
#1428
0"
#1429
1"
b1011 &
#1430
0"
#1431
1"
b1100 &
#1432
0"
#1433
1"
b1101 &
#1434
0"
#1435
1"
b1110 &
#1436
0"
#1437
1"
b1111 &
#1438
0"
#1439
1"
b0000 &
#1440
0"
#1441
1"
b0001 &
#1442
0"
#1443
1"
b0010 &
#1444
0"
#1445
1"
b0011 &
#1446
0"
#1447
1"
b0100 &
#1448
0"
#1449
1"
b0101 &
#1450
0"
#1451
1"
b0110 &
#1452
0"
#1453
1"
b0111 &
#1454
0"
#1455
1"
b1000 &
#1456
0"
#1457
1"
b1001 &
#1458
0"
#1459
1"
b1010 &
#1460
0"
#1461
1"
b1011 &
#1462
0"
#1463
1"
b1100 &
#1464
0"
#1465
1"
b1101 &
#1466
0"
#1467
1"
b1110 &
#1468
0"
#1469
1"
b1111 &
#1470
0"
#1471
1"
b0000 &
#1472
0"
#1473
1"
b0001 &
#1474
0"
#1475
1"
b0010 &
#1476
0"
#1477
1"
b0011 &
#1478
0"
#1479
1"
b0100 &
#1480
0"
#1481
1"
b0101 &
#1482
0"
#1483
1"
b0110 &
#1484
0"
#1485
1"
b0111 &
#1486
0"
#1487
1"
b1000 &
#1488
0"
#1489
1"
b1001 &
#1490
0"
#1491
1"
b1010 &
#1492
0"
#1493
1"
b1011 &
#1494
0"
#1495
1"
b1100 &
#1496
0"
#1497
1"
b1101 &
#1498
0"
#1499
1"
b1110 &
#1500
0"
#1501
1"
b1111 &
#1502
0"
#1503
1"
b0000 &
#1504
0"
#1505
1"
b0001 &
#1506
0"
#1507
1"
b0010 &
#1508
0"
#1509
1"
b0011 &
#1510
0"
#1511
1"
b0100 &
#1512
0"
#1513
1"
b0101 &
#1514
0"
#1515
1"
b0110 &
#1516
0"
#1517
1"
b0111 &
#1518
0"
#1519
1"
b1000 &
#1520
0"
#1521
1"
b1001 &
#1522
0"
#1523
1"
b1010 &
#1524
0"
#1525
1"
b1011 &
#1526
0"
#1527
1"
b1100 &
#1528
0"
#1529
1"
b1101 &
#1530
0"
#1531
1"
b1110 &
#1532
0"
#1533
1"
b1111 &
#1534
0"
#1535
1"
b0000 &
#1536
0"
#1537
1"
b0001 &
#1538
0"
#1539
1"
b0010 &
#1540
0"
#1541
1"
b0011 &
#1542
0"
#1543
1"
b0100 &
#1544
0"
#1545
1"
b0101 &
#1546
0"
#1547
1"
b0110 &
#1548
0"
#1549
1"
b0111 &
#1550
0"
#1551
1"
b1000 &
#1552
0"
#1553
1"
b1001 &
#1554
0"
#1555
1"
b1010 &
